setup.py
distributions_uworkshop/Binomialdistribution.py
distributions_uworkshop/Gaussiandistribution.py
distributions_uworkshop/Generaldistribution.py
distributions_uworkshop/__init__.py
distributions_uworkshop.egg-info/PKG-INFO
distributions_uworkshop.egg-info/SOURCES.txt
distributions_uworkshop.egg-info/dependency_links.txt
distributions_uworkshop.egg-info/not-zip-safe
distributions_uworkshop.egg-info/top_level.txt